pywe_response/__init__.py
pywe_response/response.py
pywe_response-1.0.1.dist-info/DESCRIPTION.rst
pywe_response-1.0.1.dist-info/METADATA
pywe_response-1.0.1.dist-info/RECORD
pywe_response-1.0.1.dist-info/WHEEL
pywe_response-1.0.1.dist-info/metadata.json
pywe_response-1.0.1.dist-info/top_level.txt
